StereoFractAnalyzer/StereoFractAnalyzer.py
StereoFractAnalyzer/__init__.py
tests/__init__.py
tests/test_stereofractanalyzer.py
StereoFractAnalyzer-1.0.0.dist-info/LICENSE
StereoFractAnalyzer-1.0.0.dist-info/METADATA
StereoFractAnalyzer-1.0.0.dist-info/WHEEL
StereoFractAnalyzer-1.0.0.dist-info/entry_points.txt
StereoFractAnalyzer-1.0.0.dist-info/top_level.txt
StereoFractAnalyzer-1.0.0.dist-info/RECORD
