Metadata-Version: 2.1
Name: StereoFractAnalyzer
Version: 1.0.0
Summary: The StereoFractAnalyzer class in this package is designed for fractal dimension analysis of both 3D meshes from STL files and 2D images, incorporating functionalities for geometric transformations, visualization, and fractal dimension calculation using the box counting method. It leverages libraries like open3d, numpy, matplotlib, and PIL for processing and supports command-line arguments for user convenience.
Home-page: https://github.com/kmmukut/StereoFractAnalyzer.git
Author: Khaled Mosharraf Mukut
Author-email: kmmukut@gmail.com
License: MIT
Classifier: Programming Language :: Python :: 3
Classifier: License :: OSI Approved :: MIT License
Classifier: Operating System :: OS Independent
Requires-Python: >=3.6
License-File: LICENSE
Requires-Dist: open3d
Requires-Dist: numpy
Requires-Dist: matplotlib
Requires-Dist: Pillow
Requires-Dist: argparse
